ALLCODEHERE/UART_PROTOCOL /hdl/uart_rx.v
`default_nettype none
`timescale 1ns/1ps

// Modified from Dan Gisselquist's rx_uart module,
// available at https://zipcpu.com/tutorial/ex-09-uartrx.zip

module uart_rx #(
    parameter CLOCKS_PER_BAUD = 0                       // Specify name/location of RAM initialization file if using one (leave blank if not)
) (
    input wire clk,
    input wire rx,
    output reg [7:0] data_o,
    output reg valid_o);

    localparam IDLE = 0;
    localparam BIT_ZERO = 1;
    localparam STOP_BIT = 9;

    reg	[3:0] state = IDLE;
    reg	[15:0] baud_counter = 0;
    wire zero_baud_counter;
    assign zero_baud_counter = (baud_counter == 0);

    // 2FF Synchronizer
    reg ck_uart = 1;
    reg	q_uart = 1;
    always @(posedge clk)
        { ck_uart, q_uart } <= { q_uart, rx };

    always @(posedge clk)
        if (state == IDLE) begin
            state <= IDLE;
            baud_counter <= 0;
            if (!ck_uart) begin
                state <= BIT_ZERO;
                baud_counter <= CLOCKS_PER_BAUD+CLOCKS_PER_BAUD/2-1'b1;
            end
        end

        else if (zero_baud_counter) begin
            state <= state + 1;
            baud_counter <= CLOCKS_PER_BAUD-1'b1;
            if (state == STOP_BIT) begin
                state <= IDLE;
                baud_counter <= 0;
            end
        end

        else baud_counter <= baud_counter - 1'b1;

    always @(posedge clk)
        if ( (zero_baud_counter) && (state != STOP_BIT) )
            data_o <= {ck_uart, data_o[7:1]};

    initial	valid_o = 1'b0;
    always @(posedge clk)
        valid_o <= ( (zero_baud_counter) && (state == STOP_BIT) );

endmodule

`default_nettype wire

ALLCODEHERE/UART_PROTOCOL /hdl/uart_tx.v
`default_nettype none
`timescale 1ns/1ps

module uart_tx #(
    parameter CLOCKS_PER_BAUD = 0                       // Specify name/location of RAM initialization file if using one (leave blank if not)
)(
	input wire clk,
	input wire [7:0] data_i,
	input wire start_i,
	output reg done_o,
	output reg tx);

	// this module supports only 8N1 serial at a configurable baudrate
	reg [$clog2(CLOCKS_PER_BAUD)-1:0] baud_counter = 0;

	reg [8:0] buffer = 0;
	reg [3:0] bit_index = 0;

	initial done_o = 1;
	initial tx = 1;

	always @(posedge clk) begin
		if (start_i && done_o) begin
			baud_counter <= CLOCKS_PER_BAUD - 1;
			buffer <= {1'b1, data_i};
			bit_index <= 0;
			done_o <= 0;
			tx <= 0;
		end

		else if (!done_o) begin
			baud_counter <= baud_counter - 1;
			done_o <= (baud_counter == 1) && (bit_index == 9);

			// a baud period has elapsed
			if (baud_counter == 0) begin
				baud_counter <= CLOCKS_PER_BAUD - 1;

				// clock out another bit if there are any left
				if (bit_index < 9) begin
					tx <= buffer[bit_index];
					bit_index <= bit_index + 1;
				end

				// byte has been sent, send out next one or go to idle
				else begin
					if(start_i) begin
						buffer <= {1'b1, data_i};
						bit_index <= 0;
						tx <= 0;
					end

					else done_o <= 1;
				end
			end
		end
	end
endmodule

`default_nettype wire

UART_PROTOCOL /sim/uart_rx_tb.sv
`timescale 1ns / 1ps
`default_nettype none


module uart_rx_tb();

  logic clk_in;
  logic rst_in;
  logic tx;

  logic [7:0] data_to_lidar;
  logic send_data_lidar;
  logic is_data_sent_lidar;

uart_tx #(.CLOCKS_PER_BAUD(868)) myTXLiDAR (
    .clk(clk_in),
    .data_i(data_to_lidar),
    .start_i(send_data_lidar),
    .done_o(is_data_sent_lidar),
    .tx(tx));
 
logic [7:0] data_from_lidar;
logic data_received_lidar;

uart_rx #(.CLOCKS_PER_BAUD(868)) myRXLiDAR (
    .clk(clk_in),
    .rx(tx),
    .data_o(data_from_lidar),
    .valid_o(data_received_lidar));
 
  always begin
      #5;  //every 5 ns switch...so period of clock is 10 ns...100 MHz clock
      clk_in = !clk_in;
  end
  //initial block...this is our test simulation
  initial begin
    $dumpfile("uart_rx_tb.vcd"); //file to store value change dump (vcd)
    $dumpvars(0,uart_rx_tb);
    $display("Starting Sim"); //print nice message at start
    clk_in = 0;
    data_to_lidar = 8'hEA; //16 long message, 2-wide bit duration
    #10;
    send_data_lidar = 1'b1 ; 
    #10;
    send_data_lidar = 1'b0;
    $display("trig data clk");
    for(int i=0; i<300; i=i+1)begin
      #400;
    end
    data_to_lidar = 8'hA0;
    #10;
    send_data_lidar = 1'b1;
    #10
    send_data_lidar = 1'b0;
    $display("trig data clk");
    for(int i=0; i<300; i=i+1)begin

      #300;
    end
    $display("Finishing Sim"); //print nice message at end
    $finish;
  end
endmodule
`default_nettype wire

ALLCODEHERE/UART_PROTOCOL /uart_rx_tb.vcd
$date
	Wed Nov 15 01:57:13 2023
$end
$version
	Icarus Verilog
$end
$timescale
	1ps
$end
$scope module uart_rx_tb $end
$var wire 1 ! tx $end
$var wire 1 " is_data_sent_lidar $end
$var wire 1 # data_received_lidar $end
$var wire 8 $ data_from_lidar [7:0] $end
$var reg 1 % clk_in $end
$var reg 8 & data_to_lidar [7:0] $end
$var reg 1 ' send_data_lidar $end
$scope module myRXLiDAR $end
$var wire 1 % clk $end
$var wire 1 ( zero_baud_counter $end
$var wire 1 ! rx $end
$var parameter 32 ) BIT_ZERO $end
$var parameter 32 * CLOCKS_PER_BAUD $end
$var parameter 32 + IDLE $end
$var parameter 32 , STOP_BIT $end
$var reg 16 - baud_counter [15:0] $end
$var reg 1 . ck_uart $end
$var reg 8 / data_o [7:0] $end
$var reg 1 0 q_uart $end
$var reg 4 1 state [3:0] $end
$var reg 1 # valid_o $end
$upscope $end
$scope module myTXLiDAR $end
$var wire 1 % clk $end
$var wire 8 2 data_i [7:0] $end
$var wire 1 ' start_i $end
$var parameter 32 3 CLOCKS_PER_BAUD $end
$var reg 10 4 baud_counter [9:0] $end
$var reg 4 5 bit_index [3:0] $end
$var reg 9 6 buffer [8:0] $end
$var reg 1 " done_o $end
$var reg 1 ! tx $end
$upscope $end
$scope begin $ivl_for_loop0 $end
$var integer 32 7 i [31:0] $end
$upscope $end
$scope begin $ivl_for_loop1 $end
$var integer 32 8 i [31:0] $end
$upscope $end
$upscope $end
$enddefinitions $end
$comment Show the parameter values. $end
$dumpall
b1101100100 3
b1001 ,
b0 +
b1101100100 *
b1 )
$end
#0
$dumpvars
b0 8
b0 7
b0 6
b0 5
b0 4
b11101010 2
b0 1
10
bx /
1.
b0 -
1(
x'
b11101010 &
0%
bx $
0#
1"
1!
$end
#5000
b1xxxxxxx $
b1xxxxxxx /
1%
#10000
0%
1'
#15000
b11xxxxxx $
b11xxxxxx /
0!
0"
b111101010 6
b1101100011 4
1%
#20000
0%
0'
#25000
b1101100010 4
00
b111xxxxx $
b111xxxxx /
1%
#30000
0%
#35000
b1111xxxx $
b1111xxxx /
0.
b1101100001 4
1%
#40000
0%
#45000
b1101100000 4
0(
b10100010101 -
b1 1
b1111xxx $
b1111xxx /
1%
#50000
0%
#55000
b10100010100 -
b1101011111 4
1%
#60000
0%
#65000
b1101011110 4
b10100010011 -
1%
#70000
0%
#75000
b10100010010 -
b1101011101 4
1%
#80000
0%
#85000
b1101011100 4
b10100010001 -
1%
#90000
0%
#95000
b10100010000 -
b1101011011 4
1%
#100000
0%
#105000
b1101011010 4
b10100001111 -
1%
#110000
0%
#115000
b10100001110 -
b1101011001 4
1%
#120000
0%
#125000
b1101011000 4
b10100001101 -
1%
#130000
0%
#135000
b10100001100 -
b1101010111 4
1%
#140000
0%
#145000
b1101010110 4
b10100001011 -
1%
#150000
0%
#155000
b10100001010 -
b1101010101 4
1%
#160000
0%
#165000
b1101010100 4
b10100001001 -
1%
#170000
0%
#175000
b10100001000 -
b1101010011 4
1%
#180000
0%
#185000
b1101010010 4
b10100000111 -
1%
#190000
0%
#195000
b10100000110 -
b1101010001 4
1%
#200000
0%
#205000
b1101010000 4
b10100000101 -
1%
#210000
0%
#215000
b10100000100 -
b1101001111 4
1%
#220000
0%
#225000
b1101001110 4
b10100000011 -
1%
#230000
0%
#235000
b10100000010 -
b1101001101 4
1%
#240000
0%
#245000
b1101001100 4
b10100000001 -
1%
#250000
0%
#255000
b10100000000 -
b1101001011 4
1%
#260000
0%
#265000
b1101001010 4
b10011111111 -
1%
#270000
0%
#275000
b10011111110 -
b1101001001 4
1%
#280000
0%
#285000
b1101001000 4
b10011111101 -
1%
#290000
0%
#295000
b10011111100 -
b1101000111 4
1%
#300000
0%
#305000
b1101000110 4
b10011111011 -
1%
#310000
0%
#315000
b10011111010 -
b1101000101 4
1%
#320000
0%
#325000
b1101000100 4
b10011111001 -
1%
#330000
0%
#335000
b10011111000 -
b1101000011 4
1%
#340000
0%
#345000
b1101000010 4
b10011110111 -
1%
#350000
0%
#355000
b10011110110 -
b1101000001 4
1%
#360000
0%
#365000
b1101000000 4
b10011110101 -
1%
#370000
0%
#375000
b10011110100 -
b1100111111 4
1%
#380000
0%
#385000
b1100111110 4
b10011110011 -
1%
#390000
0%
#395000
b10011110010 -
b1100111101 4
1%
#400000
0%
#405000
b1100111100 4
b10011110001 -
1%
#410000
0%
#415000
b10011110000 -
b1100111011 4
1%
#420000
0%
b1 7
#425000
b1100111010 4
b10011101111 -
1%
#430000
0%
#435000
b10011101110 -
b1100111001 4
1%
#440000
0%
#445000
b1100111000 4
b10011101101 -
1%
#450000
0%
#455000
b10011101100 -
b1100110111 4
1%
#460000
0%
#465000
b1100110110 4
b10011101011 -
1%
#470000
0%
#475000
b10011101010 -
b1100110101 4
1%
#480000
0%
#485000
b1100110100 4
b10011101001 -
1%
#490000
0%
#495000
b10011101000 -
b1100110011 4
1%
#500000
0%
#505000
b1100110010 4
b10011100111 -
1%
#510000
0%
#515000
b10011100110 -
b1100110001 4
1%
#520000
0%
#525000
b1100110000 4
b10011100101 -
1%
#530000
0%
#535000
b10011100100 -
b1100101111 4
1%
#540000
0%
#545000
b1100101110 4
b10011100011 -
1%
#550000
0%
#555000
b10011100010 -
b1100101101 4
1%
#560000
0%
#565000
b1100101100 4
b10011100001 -
1%
#570000
0%
#575000
b10011100000 -
b1100101011 4
1%
#580000
0%
#585000
b1100101010 4
b10011011111 -
1%
#590000
0%
#595000
b10011011110 -
b1100101001 4
1%
#600000
0%
#605000
b1100101000 4
b10011011101 -
1%
#610000
0%
#615000
b10011011100 -
b1100100111 4
1%
#620000
0%
#625000
b1100100110 4
b10011011011 -
1%
#630000
0%
#635000
b10011011010 -
b1100100101 4
1%
#640000
0%
#645000
b1100100100 4
b10011011001 -
1%
#650000
0%
#655000
b10011011000 -
b1100100011 4
1%
#660000
0%
#665000
b1100100010 4
b10011010111 -
1%
#670000
0%
#675000
b10011010110 -
b1100100001 4
1%
#680000
0%
#685000
b1100100000 4
b10011010101 -
1%
#690000
0%
#695000
b10011010100 -
b1100011111 4
1%
#700000
0%
#705000
b1100011110 4
b10011010011 -
1%
#710000
0%
#715000
b10011010010 -
b1100011101 4
1%
#720000
0%
#725000
b1100011100 4
b10011010001 -
1%
#730000
0%
#735000
b10011010000 -
b1100011011 4
1%
#740000
0%
#745000
b1100011010 4
b10011001111 -
1%
#750000
0%
#755000
b10011001110 -
b1100011001 4
1%
#760000
0%
#765000
b1100011000 4
b10011001101 -
1%
#770000
0%
#775000
b10011001100 -
b1100010111 4
1%
#780000
0%
#785000
b1100010110 4
b10011001011 -
1%
#790000
0%
#795000
b10011001010 -
b1100010101 4
1%
#800000
0%
#805000
b1100010100 4
b10011001001 -
1%
#810000
0%
#815000
b10011001000 -
b1100010011 4
1%
#820000
0%
b10 7
#825000
b1100010010 4
b10011000111 -
1%
#830000
0%
#835000
b10011000110 -
b1100010001 4
1%
#840000
0%
#845000
b1100010000 4
b10011000101 -
1%
#850000
0%
#855000
b10011000100 -
b1100001111 4
1%
#860000
0%
#865000
b1100001110 4
b10011000011 -
1%
#870000
0%
#875000
b10011000010 -
b1100001101 4
1%
#880000
0%
#885000
b1100001100 4
b10011000001 -
1%
#890000
0%
#895000
b10011000000 -
b1100001011 4
1%
#900000
0%
#905000
b1100001010 4
b10010111111 -
1%
#910000
0%
#915000
b10010111110 -
b1100001001 4
1%
#920000
0%
#925000
b1100001000 4
b10010111101 -
1%
#930000
0%
#935000
b10010111100 -
b1100000111 4
1%
#940000
0%
#945000
b1100000110 4
b10010111011 -
1%
#950000
0%
#955000
b10010111010 -
b1100000101 4
1%
#960000
0%
#965000
b1100000100 4
b10010111001 -
1%
#970000
0%
#975000
b10010111000 -
b1100000011 4
1%
#980000
0%
#985000
b1100000010 4
b10010110111 -
1%
#990000
0%
#995000
b10010110110 -
b1100000001 4
1%
#1000000
0%
#1005000
b1100000000 4
b10010110101 -
1%
#1010000
0%
#1015000
b10010110100 -
b1011111111 4
1%
#1020000
0%
#1025000
b1011111110 4
b10010110011 -
1%
#1030000
0%
#1035000
b10010110010 -
b1011111101 4
1%
#1040000
0%
#1045000
b1011111100 4
b10010110001 -
1%
#1050000
0%
#1055000
b10010110000 -
b1011111011 4
1%
#1060000
0%
#1065000
b1011111010 4
b10010101111 -
1%
#1070000
0%
#1075000
b10010101110 -
b1011111001 4
1%
#1080000
0%
#1085000
b1011111000 4
b10010101101 -
1%
#1090000
0%
#1095000
b10010101100 -
b1011110111 4
1%
#1100000
0%
#1105000
b1011110110 4
b10010101011 -
1%
#1110000
0%
#1115000
b10010101010 -
b1011110101 4
1%
#1120000
0%
#1125000
b1011110100 4
b10010101001 -
1%
#1130000
0%
#1135000
b10010101000 -
b1011110011 4
1%
#1140000
0%
#1145000
b1011110010 4
b10010100111 -
1%
#1150000
0%
#1155000
b10010100110 -
b1011110001 4
1%
#1160000
0%
#1165000
b1011110000 4
b10010100101 -
1%
#1170000
0%
#1175000
b10010100100 -
b1011101111 4
1%
#1180000
0%
#1185000
b1011101110 4
b10010100011 -
1%
#1190000
0%
#1195000
b10010100010 -
b1011101101 4
1%
#1200000
0%
#1205000
b1011101100 4
b10010100001 -
1%
#1210000
0%
#1215000
b10010100000 -
b1011101011 4
1%
#1220000
0%
b11 7
#1225000
b1011101010 4
b10010011111 -
1%
#1230000
0%
#1235000
b10010011110 -
b1011101001 4
1%
#1240000
0%
#1245000
b1011101000 4
b10010011101 -
1%
#1250000
0%
#1255000
b10010011100 -
b1011100111 4
1%
#1260000
0%
#1265000
b1011100110 4
b10010011011 -
1%
#1270000
0%
#1275000
b10010011010 -
b1011100101 4
1%
#1280000
0%
#1285000
b1011100100 4
b10010011001 -
1%
#1290000
0%
#1295000
b10010011000 -
b1011100011 4
1%
#1300000
0%
#1305000
b1011100010 4
b10010010111 -
1%
#1310000
0%
#1315000
b10010010110 -
b1011100001 4
1%
#1320000
0%
#1325000
b1011100000 4
b10010010101 -
1%
#1330000
0%
#1335000
b10010010100 -
b1011011111 4
1%
#1340000
0%
#1345000
b1011011110 4
b10010010011 -
1%
#1350000
0%
#1355000
b10010010010 -
b1011011101 4
1%
#1360000
0%
#1365000
b1011011100 4
b10010010001 -
1%
#1370000
0%
#1375000
b10010010000 -
b1011011011 4
1%
#1380000
0%
#1385000
b1011011010 4
b10010001111 -
1%
#1390000
0%
#1395000
b10010001110 -
b1011011001 4
1%
#1400000
0%
#1405000
b1011011000 4
b10010001101 -
1%
#1410000
0%
#1415000
b10010001100 -
b1011010111 4
1%
#1420000
0%
#1425000
b1011010110 4
b10010001011 -
1%
#1430000
0%
#1435000
b10010001010 -
b1011010101 4
1%
#1440000
0%
#1445000
b1011010100 4
b10010001001 -
1%
#1450000
0%
#1455000
b10010001000 -
b1011010011 4
1%
#1460000
0%
#1465000
b1011010010 4
b10010000111 -
1%
#1470000
0%
#1475000
b10010000110 -
b1011010001 4
1%
#1480000
0%
#1485000
b1011010000 4
b10010000101 -
1%
#1490000
0%
#1495000
b10010000100 -
b1011001111 4
1%
#1500000
0%
#1505000
b1011001110 4
b10010000011 -
1%
#1510000
0%
#1515000
b10010000010 -
b1011001101 4
1%
#1520000
0%
#1525000
b1011001100 4
b10010000001 -
1%
#1530000
0%
#1535000
b10010000000 -
b1011001011 4
1%
#1540000
0%
#1545000
b1011001010 4
b10001111111 -
1%
#1550000
0%
#1555000
b10001111110 -
b1011001001 4
1%
#1560000
0%
#1565000
b1011001000 4
b10001111101 -
1%
#1570000
0%
#1575000
b10001111100 -
b1011000111 4
1%
#1580000
0%
#1585000
b1011000110 4
b10001111011 -
1%
#1590000
0%
#1595000
b10001111010 -
b1011000101 4
1%
#1600000
0%
#1605000
b1011000100 4
b10001111001 -
1%
#1610000
0%
#1615000
b10001111000 -
b1011000011 4
1%
#1620000
0%
b100 7
#1625000
b1011000010 4
b10001110111 -
1%
#1630000
0%
#1635000
b10001110110 -
b1011000001 4
1%
#1640000
0%
#1645000
b1011000000 4
b10001110101 -
1%
#1650000
0%
#1655000
b10001110100 -
b1010111111 4
1%
#1660000
0%
#1665000
b1010111110 4
b10001110011 -
1%
#1670000
0%
#1675000
b10001110010 -
b1010111101 4
1%
#1680000
0%
#1685000
b1010111100 4
b10001110001 -
1%
#1690000
0%
#1695000
b10001110000 -
b1010111011 4
1%
#1700000
0%
#1705000
b1010111010 4
b10001101111 -
1%
#1710000
0%
#1715000
b10001101110 -
b1010111001 4
1%
#1720000
0%
#1725000
b1010111000 4
b10001101101 -
1%
#1730000
0%
#1735000
b10001101100 -
b1010110111 4
1%
#1740000
0%
#1745000
b1010110110 4
b10001101011 -
1%
#1750000
0%
#1755000
b10001101010 -
b1010110101 4
1%
#1760000
0%
#1765000
b1010110100 4
b10001101001 -
1%
#1770000
0%
#1775000
b10001101000 -
b1010110011 4
1%
#1780000
0%
#1785000
b1010110010 4
b10001100111 -
1%
#1790000
0%
#1795000
b10001100110 -
b1010110001 4
1%
#1800000
0%
#1805000
b1010110000 4
b10001100101 -
1%
#1810000
0%
#1815000
b10001100100 -
b1010101111 4
1%
#1820000
0%
#1825000
b1010101110 4
b10001100011 -
1%
#1830000
0%
#1835000
b10001100010 -
b1010101101 4
1%
#1840000
0%
#1845000
b1010101100 4
b10001100001 -
1%
#1850000
0%
#1855000
b10001100000 -
b1010101011 4
1%
#1860000
0%
#1865000
b1010101010 4
b10001011111 -
1%
#1870000
0%
#1875000
b10001011110 -
b1010101001 4
1%
#1880000
0%
#1885000
b1010101000 4
b10001011101 -
1%
#1890000
0%
#1895000
b10001011100 -
b1010100111 4
1%
#1900000
0%
#1905000
b1010100110 4
b10001011011 -
1%
#1910000
0%
#1915000
b10001011010 -
b1010100101 4
1%
#1920000
0%
#1925000
b1010100100 4
b10001011001 -
1%
#1930000
0%
#1935000
b10001011000 -
b1010100011 4
1%
#1940000
0%
#1945000
b1010100010 4
b10001010111 -
1%
#1950000
0%
#1955000
b10001010110 -
b1010100001 4
1%
#1960000
0%
#1965000
b1010100000 4
b10001010101 -
1%
#1970000
0%
#1975000
b10001010100 -
b1010011111 4
1%
#1980000
0%
#1985000
b1010011110 4
b10001010011 -
1%
#1990000
0%
#1995000
b10001010010 -
b1010011101 4
1%
#2000000
0%
#2005000
b1010011100 4
b10001010001 -
1%
#2010000
0%
#2015000
b10001010000 -
b1010011011 4
1%
#2020000
0%
b101 7
#2025000
b1010011010 4
b10001001111 -
1%
#2030000
0%
#2035000
b10001001110 -
b1010011001 4
1%
#2040000
0%
#2045000
b1010011000 4
b10001001101 -
1%
#2050000
0%
#2055000
b10001001100 -
b1010010111 4
1%
#2060000
0%
#2065000
b1010010110 4
b10001001011 -
1%
#2070000
0%
#2075000
b10001001010 -
b1010010101 4
1%
#2080000
0%
#2085000
b1010010100 4
b10001001001 -
1%
#2090000
0%
#2095000
b10001001000 -
b1010010011 4
1%
#2100000
0%
#2105000
b1010010010 4
b10001000111 -
1%
#2110000
0%
#2115000
b10001000110 -
b1010010001 4
1%
#2120000
0%
#2125000
b1010010000 4
b10001000101 -
1%
#2130000
0%
#2135000
b10001000100 -
b1010001111 4
1%
#2140000
0%
#2145000
b1010001110 4
b10001000011 -
1%
#2150000
0%
#2155000
b10001000010 -
b1010001101 4
1%
#2160000
0%
#2165000
b1010001100 4
b10001000001 -
1%
#2170000
0%
#2175000
b10001000000 -
b1010001011 4
1%
#2180000
0%
#2185000
b1010001010 4
b10000111111 -
1%
#2190000
0%
#2195000
b10000111110 -
b1010001001 4
1%
#2200000
0%
#2205000
b1010001000 4
b10000111101 -
1%
#2210000
0%
#2215000
b10000111100 -
b1010000111 4
1%
#2220000
0%
#2225000
b1010000110 4
b10000111011 -
1%
#2230000
0%
#2235000
b10000111010 -
b1010000101 4
1%
#2240000
0%
#2245000
b1010000100 4
b10000111001 -
1%
#2250000
0%
#2255000
b10000111000 -
b1010000011 4
1%
#2260000
0%
#2265000
b1010000010 4
b10000110111 -
1%
#2270000
0%
#2275000
b10000110110 -
b1010000001 4
1%
#2280000
0%
#2285000
b1010000000 4
b10000110101 -
1%
#2290000
0%
#2295000
b10000110100 -
b1001111111 4
1%
#2300000
0%
#2305000
b1001111110 4
b10000110011 -
1%
#2310000
0%
#2315000
b10000110010 -
b1001111101 4
1%
#2320000
0%
#2325000
b1001111100 4
b10000110001 -
1%
#2330000
0%
#2335000
b10000110000 -
b1001111011 4
1%
#2340000
0%
#2345000
b1001111010 4
b10000101111 -
1%
#2350000
0%
#2355000
b10000101110 -
b1001111001 4
1%
#2360000
0%
#2365000
b1001111000 4
b10000101101 -
1%
#2370000
0%
#2375000
b10000101100 -
b1001110111 4
1%
#2380000
0%
#2385000
b1001110110 4
b10000101011 -
1%
#2390000
0%
#2395000
b10000101010 -
b1001110101 4
1%
#2400000
0%
#2405000
b1001110100 4
b10000101001 -
1%
#2410000
0%
#2415000
b10000101000 -
b1001110011 4
1%
#2420000
0%
b110 7
#2425000
b1001110010 4
b10000100111 -
1%
#2430000
0%
#2435000
b10000100110 -
b1001110001 4
1%
#2440000
0%
#2445000
b1001110000 4
b10000100101 -
1%
#2450000
0%
#2455000
b10000100100 -
b1001101111 4
1%
#2460000
0%
#2465000
b1001101110 4
b10000100011 -
1%
#2470000
0%
#2475000
b10000100010 -
b1001101101 4
1%
#2480000
0%
#2485000
b1001101100 4
b10000100001 -
1%
#2490000
0%
#2495000
b10000100000 -
b1001101011 4
1%
#2500000
0%
#2505000
b1001101010 4
b10000011111 -
1%
#2510000
0%
#2515000
b10000011110 -
b1001101001 4
1%
#2520000
0%
#2525000
b1001101000 4
b10000011101 -
1%
#2530000
0%
#2535000
b10000011100 -
b1001100111 4
1%
#2540000
0%
#2545000
b1001100110 4
b10000011011 -
1%
#2550000
0%
#2555000
b10000011010 -
b1001100101 4
1%
#2560000
0%
#2565000
b1001100100 4
b10000011001 -
1%
#2570000
0%
#2575000
b10000011000 -
b1001100011 4
1%
#2580000
0%
#2585000
b1001100010 4
b10000010111 -
1%
#2590000
0%
#2595000
b10000010110 -
b1001100001 4
1%
#2600000
0%
#2605000
b1001100000 4
b10000010101 -
1%
#2610000
0%
#2615000
b10000010100 -
b1001011111 4
1%
#2620000
0%
#2625000
b1001011110 4
b10000010011 -
1%
#2630000
0%
#2635000
b10000010010 -
b1001011101 4
1%
#2640000
0%
#2645000
b1001011100 4
b10000010001 -
1%
#2650000
0%
#2655000
b10000010000 -
b1001011011 4
1%
#2660000
0%
#2665000
b1001011010 4
b10000001111 -
1%
#2670000
0%
#2675000
b10000001110 -
b1001011001 4
1%
#2680000
0%
#2685000
b1001011000 4
b10000001101 -
1%
#2690000
0%
#2695000
b10000001100 -
b1001010111 4
1%
#2700000
0%
#2705000
b1001010110 4
b10000001011 -
1%
#2710000
0%
#2715000
b10000001010 -
b1001010101 4
1%
#2720000
0%
#2725000
b1001010100 4
b10000001001 -
1%
#2730000
0%
#2735000
b10000001000 -
b1001010011 4
1%
#2740000
0%
#2745000
b1001010010 4
b10000000111 -
1%
#2750000
0%
#2755000
b10000000110 -
b1001010001 4
1%
#2760000
0%
#2765000
b1001010000 4
b10000000101 -
1%
#2770000
0%
#2775000
b10000000100 -
b1001001111 4
1%
#2780000
0%
#2785000
b1001001110 4
b10000000011 -
1%
#2790000
0%
#2795000
b10000000010 -
b1001001101 4
1%
#2800000
0%
#2805000
b1001001100 4
b10000000001 -
1%
#2810000
0%
#2815000
b10000000000 -
b1001001011 4
1%
#2820000
0%
b111 7
#2825000
b1001001010 4
b1111111111 -
1%
#2830000
0%
#2835000
b1111111110 -
b1001001001 4
1%
#2840000
0%
#2845000
b1001001000 4
b1111111101 -
1%
#2850000
0%
#2855000
b1111111100 -
b1001000111 4
1%
#2860000
0%
#2865000
b1001000110 4
b1111111011 -
1%
#2870000
0%
#2875000
b1111111010 -
b1001000101 4
1%
#2880000
0%
#2885000
b1001000100 4
b1111111001 -
1%
#2890000
0%
#2895000
b1111111000 -
b1001000011 4
1%
#2900000
0%
#2905000
b1001000010 4
b1111110111 -
1%
#2910000
0%
#2915000
b1111110110 -
b1001000001 4
1%
#2920000
0%
#2925000
b1001000000 4
b1111110101 -
1%
#2930000
0%
#2935000
b1111110100 -
b1000111111 4
1%
#2940000
0%
#2945000
b1000111110 4
b1111110011 -
1%
#2950000
0%
#2955000
b1111110010 -
b1000111101 4
1%
#2960000
0%
#2965000
b1000111100 4
b1111110001 -
1%
#2970000
0%
#2975000
b1111110000 -
b1000111011 4
1%
#2980000
0%
#2985000
b1000111010 4
b1111101111 -
1%
#2990000
0%
#2995000
b1111101110 -
b1000111001 4
1%
#3000000
0%
#3005000
b1000111000 4
b1111101101 -
1%
#3010000
0%
#3015000
b1111101100 -
b1000110111 4
1%
#3020000
0%
#3025000
b1000110110 4
b1111101011 -
1%
#3030000
0%
#3035000
b1111101010 -
b1000110101 4
1%
#3040000
0%
#3045000
b1000110100 4
b1111101001 -
1%
#3050000
0%
#3055000
b1111101000 -
b1000110011 4
1%
#3060000
0%
#3065000
b1000110010 4
b1111100111 -
1%
#3070000
0%
#3075000
b1111100110 -
b1000110001 4
1%
#3080000
0%
#3085000
b1000110000 4
b1111100101 -
1%
#3090000
0%
#3095000
b1111100100 -
b1000101111 4
1%
#3100000
0%
#3105000
b1000101110 4
b1111100011 -
1%
#3110000
0%
#3115000
b1111100010 -
b1000101101 4
1%
#3120000
0%
#3125000
b1000101100 4
b1111100001 -
1%
#3130000
0%
#3135000
b1111100000 -
b1000101011 4
1%
#3140000
0%
#3145000
b1000101010 4
b1111011111 -
1%
#3150000
0%
#3155000
b1111011110 -
b1000101001 4
1%
#3160000
0%
#3165000
b1000101000 4
b1111011101 -
1%
#3170000
0%
#3175000
b1111011100 -
b1000100111 4
1%
#3180000
0%
#3185000
b1000100110 4
b1111011011 -
1%
#3190000
0%
#3195000
b1111011010 -
b1000100101 4
1%
#3200000
0%
#3205000
b1000100100 4
b1111011001 -
1%
#3210000
0%
#3215000
b1111011000 -
b1000100011 4
1%
#3220000
0%
b1000 7
#3225000
b1000100010 4
b1111010111 -
1%
#3230000
0%
#3235000
b1111010110 -
b1000100001 4
1%
#3240000
0%
#3245000
b1000100000 4
b1111010101 -
1%
#3250000
0%
#3255000
b1111010100 -
b1000011111 4
1%
#3260000
0%
#3265000
b1000011110 4
b1111010011 -
1%
#3270000
0%
#3275000
b1111010010 -
b1000011101 4
1%
#3280000
0%
#3285000
b1000011100 4
b1111010001 -
1%
#3290000
0%
#3295000
b1111010000 -
b1000011011 4
1%
#3300000
0%
#3305000
b1000011010 4
b1111001111 -
1%
#3310000
0%
#3315000
b1111001110 -
b1000011001 4
1%
#3320000
0%
#3325000
b1000011000 4
b1111001101 -
1%
#3330000
0%
#3335000
b1111001100 -
b1000010111 4
1%
#3340000
0%
#3345000
b1000010110 4
b1111001011 -
1%
#3350000
0%
#3355000
b1111001010 -
b1000010101 4
1%
#3360000
0%
#3365000
b1000010100 4
b1111001001 -
1%
#3370000
0%
#3375000
b1111001000 -
b1000010011 4
1%
#3380000
0%
#3385000
b1000010010 4
b1111000111 -
1%
#3390000
0%
#3395000
b1111000110 -
b1000010001 4
1%
#3400000
0%
#3405000
b1000010000 4
b1111000101 -
1%
#3410000
0%
#3415000
b1111000100 -
b1000001111 4
1%
#3420000
0%
#3425000
b1000001110 4
b1111000011 -
1%
#3430000
0%
#3435000
b1111000010 -
b1000001101 4
1%
#3440000
0%
#3445000
b1000001100 4
b1111000001 -
1%
#3450000
0%
#3455000
b1111000000 -
b1000001011 4
1%
#3460000
0%
#3465000
b1000001010 4
b1110111111 -
1%
#3470000
0%
#3475000
b1110111110 -
b1000001001 4
1%
#3480000
0%
#3485000
b1000001000 4
b1110111101 -
1%
#3490000
0%
#3495000
b1110111100 -
b1000000111 4
1%
#3500000
0%
#3505000
b1000000110 4
b1110111011 -
1%
#3510000
0%
#3515000
b1110111010 -
b1000000101 4
1%
#3520000
0%
#3525000
b1000000100 4
b1110111001 -
1%
#3530000
0%
#3535000
b1110111000 -
b1000000011 4
1%
#3540000
0%
#3545000
b1000000010 4
b1110110111 -
1%
#3550000
0%
#3555000
b1110110110 -
b1000000001 4
1%
#3560000
0%
#3565000
b1000000000 4
b1110110101 -
1%
#3570000
0%
#3575000
b1110110100 -
b111111111 4
1%
#3580000
0%
#3585000
b111111110 4
b1110110011 -
1%
#3590000
0%
#3595000
b1110110010 -
b111111101 4
1%
#3600000
0%
#3605000
b111111100 4
b1110110001 -
1%
#3610000
0%
#3615000
b1110110000 -
b111111011 4
1%
#3620000
0%
b1001 7
#3625000
b111111010 4
b1110101111 -
1%
#3630000
0%
#3635000
b1110101110 -
b111111001 4
1%
#3640000
0%
#3645000
b111111000 4
b1110101101 -
1%
#3650000
0%
#3655000
b1110101100 -
b111110111 4
1%
#3660000
0%
#3665000
b111110110 4
b1110101011 -
1%
#3670000
0%
#3675000
b1110101010 -
b111110101 4
1%
#3680000
0%
#3685000
b111110100 4
b1110101001 -
1%
#3690000
0%
#3695000
b1110101000 -
b111110011 4
1%
#3700000
0%
#3705000
b111110010 4
b1110100111 -
1%
#3710000
0%
#3715000
b1110100110 -
b111110001 4
1%
#3720000
0%
