visualizer/lec09/hdl/divider.sv
`timescale 1ns / 1ps
`default_nettype none

module divider #(parameter WIDTH = 32) (input wire clk_in,
                input wire rst_in,
                input wire[WIDTH-1:0] dividend_in,
                input wire[WIDTH-1:0] divisor_in,
                input wire data_valid_in,
                output logic[WIDTH-1:0] quotient_out,
                output logic[WIDTH-1:0] remainder_out,
                output logic data_valid_out,
                output logic error_out,
                output logic busy_out);
  logic [WIDTH-1:0] quotient, dividend;
  logic [WIDTH-1:0] divisor;
  enum {RESTING, DIVIDING} state;
  always_ff @(posedge clk_in)begin
    if (rst_in)begin
      quotient <= 0;
      dividend <= 0;
      divisor <= 0;
      remainder_out <= 0;
      busy_out <= 1'b0;
      error_out <= 1'b0;
      state <= RESTING;
      data_valid_out <= 1'b0;
    end else begin
      case (state)
        RESTING: begin
          if (data_valid_in)begin
            state <= DIVIDING;
            quotient <= 0;
            dividend <= dividend_in;
            divisor <= divisor_in;
            busy_out <= 1'b1;
            error_out <= 1'b0;
          end
          data_valid_out <= 1'b0;
        end
        DIVIDING: begin
          if (dividend<=0)begin
            state <= RESTING; //similar to return statement
            remainder_out <= dividend;
            quotient_out <= quotient;
            busy_out <= 1'b0; //tell outside world i'm done
            error_out <= 1'b0;
            data_valid_out <= 1'b1; //good stuff!
          end else if (divisor==0)begin
            state <= RESTING;
            remainder_out <= 0;
            quotient_out <= 0;
            busy_out <= 1'b0; //tell outside world i'm done
            error_out <= 1'b1; //ERROR
            data_valid_out <= 1'b1; //valid ERROR
          end else if (dividend < divisor) begin
            state <= RESTING;
            remainder_out <= dividend;
            quotient_out <= quotient;
            busy_out <= 1'b0;
            error_out <= 1'b0;
            data_valid_out <= 1'b1; //good stuff!
          end else begin
            //state staying in.
            state <= DIVIDING;
            quotient <= quotient + 1'b1;
            dividend <= dividend-divisor;
          end
        end
      endcase
    end
  end
endmodule

`default_nettype wire

visualizer/hdl/center_of_mass.sv
`timescale 1ns / 1ps
`default_nettype none

module center_of_mass (
                         input wire clk_in,
                         input wire rst_in,
                         input wire [10:0] x_in,
                         input wire [9:0]  y_in,
                         input wire valid_in,
                         input wire tabulate_in,
                         output logic [10:0] x_out,
                         output logic [9:0] y_out,
                         output logic valid_out);

  //your design here!

localparam total_pixels = 1024*768 ; 
logic [31:0] sum_of_y_pixels ; 
logic [31:0] sum_of_x_pixels ; 
logic [31:0] tally_of_pixels ; 
logic [31:0] remainder_x;
logic [31:0] remainder_y;
logic [31:0] quotient_x ;
logic [31:0] quotient_y;

logic valid_division; 
logic valid_out_x ; 
logic valid_out_y ; 
logic error_x ;
logic error_y ; 
logic busy_x ; 
logic busy_y ;
logic finish_x ;
logic finish_y ; 




divider mydividerx ( .clk_in(clk_in),
                  .rst_in(rst_in),
                  .dividend_in(sum_of_x_pixels),
                  .divisor_in(tally_of_pixels),
                  .data_valid_in(valid_division),
                  .quotient_out(quotient_x),
                  .remainder_out(remainder_x),
                  .data_valid_out(valid_out_x),
                  .error_out(error_x),
                  .busy_out(busy_x));

divider mydividery ( .clk_in(clk_in),
                  .rst_in(rst_in),
                  .dividend_in(sum_of_y_pixels),
                  .divisor_in(tally_of_pixels),
                  .data_valid_in(valid_division),
                  .quotient_out(quotient_y),
                  .remainder_out(remainder_y),
                  .data_valid_out(valid_out_y),
                  .error_out(error_y),
                  .busy_out(busy_y));
 

  typedef enum {SUMMING=0, VALID_NUMBERS=1, START_DIVISION=2, WAIT_DIVISION=3, OUTPUT_DIVISION=4, RESET = 5} processing_state ;
  processing_state state; //state of system!
always_ff @(posedge clk_in) begin 
  if(rst_in) begin
    x_out <= 0 ;
    y_out <= 0 ;
    sum_of_x_pixels <= 0 ;
    sum_of_y_pixels <= 0 ;
    tally_of_pixels <= 0 ; 
    valid_division <= 0 ;
    valid_out <= 0 ;
  end else begin
    case(state) 
    SUMMING:
    begin
      if(valid_in) begin 
        sum_of_x_pixels <= sum_of_x_pixels + x_in ; 
        sum_of_y_pixels <= sum_of_y_pixels + y_in ;
        tally_of_pixels <= tally_of_pixels +   1  ;
      end 
      state <= tabulate_in ? VALID_NUMBERS : SUMMING ;
    end
    VALID_NUMBERS:
    begin
      if(tally_of_pixels == 0 ) begin 
        state <= RESET ; 
      end else begin 
        state <= START_DIVISION ;
      end 
    end
    START_DIVISION:
    begin
      valid_division <= 1 ; 
      state <= (busy_y == 1 || busy_x == 1 ) ? WAIT_DIVISION : START_DIVISION ; 
    end
    WAIT_DIVISION:
    begin
      valid_division <= 0 ; 
      x_out <= valid_out_x ? quotient_x[10:0]: x_out ;
      y_out <= valid_out_y ? quotient_y[9:0]: y_out ;
      state <= (busy_y == 0 && busy_x == 0 ) ? OUTPUT_DIVISION : WAIT_DIVISION ; 
    end
    OUTPUT_DIVISION:
    begin
      x_out <= valid_out_x ? quotient_x[10:0]: x_out ;
      y_out <= valid_out_y ? quotient_y[9:0]: y_out ;
      state <= RESET ; 
      valid_out <= 1 ;
    end
    RESET:
    begin
      state <= SUMMING; 
      sum_of_x_pixels <= 0 ;
      sum_of_y_pixels <= 0 ;
      tally_of_pixels <= 0 ; 
      valid_out <= 0 ; 
    end 
    endcase
  end
end


endmodule


`default_nettype wire

visualizer/sim/com_tb.sv
`timescale 1ns / 1ps
`default_nettype none

module com_tb;

    //make logics for inputs and outputs!
    logic clk_in;
    logic rst_in;
    logic [10:0] x_in;
    logic [9:0] y_in;
    logic valid_in;
    logic tabulate_in;
    logic [10:0] x_out;
    logic [9:0] y_out;
    logic valid_out;

    center_of_mass uut(.clk_in(clk_in), .rst_in(rst_in),
                         .x_in(x_in),
                         .y_in(y_in),
                         .valid_in(valid_in),
                         .tabulate_in(tabulate_in),
                         .x_out(x_out),
                         .y_out(y_out),
                         .valid_out(valid_out));
    always begin
        #5;  //every 5 ns switch...so period of clock is 10 ns...100 MHz clock
        clk_in = !clk_in;
    end

    //initial block...this is our test simulation
    initial begin
        $dumpfile("com.vcd"); //file to store value change dump (vcd)
        $dumpvars(0,com_tb); //store everything at the current level and below
        $display("Starting Sim"); //print nice message
        clk_in = 0; //initialize clk (super important)
        rst_in = 0; //initialize rst (super important)
        x_in = 11'b0;
        y_in = 10'b0;
        valid_in = 0;
        tabulate_in = 0;
        #10  //wait a little bit of time at beginning
        rst_in = 1; //reset system
        #10; //hold high for a few clock cycles
        rst_in=0;
        #10;
        for (int i = 0; i<1000; i= i+1)begin
          x_in = i;
          y_in = i/2;
          valid_in = 1;
          #10;
        end
        valid_in = 0;
        #100;
        tabulate_in = 1;
        #10000;

        // Second pass 
        x_in = 11'b0;
        y_in = 10'b0;
        valid_in = 0;
        tabulate_in = 0;
        #10  //wait a little bit of time at beginning
        rst_in = 1; //reset system
        #10; //hold high for a few clock cycles
        rst_in=0;
        #10;
        for (int i = 0; i<700; i= i+1)begin
          x_in = i;
          y_in = i;
          valid_in = 1;
          #10;
        end
        valid_in = 0;
        #100;
        tabulate_in = 1;
        #10000;



  


        // Third Pass
        x_in = 11'b0;
        y_in = 10'b0;
        valid_in = 0;
        tabulate_in = 0;
        #10  //wait a little bit of time at beginning
        rst_in = 1; //reset system
        #10; //hold high for a few clock cycles
        rst_in=0;
        #10;
        y_in = 10;
        for (int i = 0; i<1000; i= i+1)begin
          x_in = i;
          
          valid_in = 1;
          #10;
        end
        valid_in = 0;
        #100;
        tabulate_in = 1;
        #10000;

        // Fourth Pass 
        x_in = 11'b0;
        y_in = 10'b0;
        valid_in = 0;
        tabulate_in = 0;
        #10  //wait a little bit of time at beginning
        rst_in = 1; //reset system
        #10; //hold high for a few clock cycles
        rst_in=0;
        #10;
        y_in = 10;
        for (int i = 0; i<1000; i= i+1)begin
          x_in = i;
          
          valid_in = 0;
          #10;
        end
        valid_in = 0;
        #100;
        tabulate_in = 1;
        #10000;


        $display("Finishing Sim"); //print nice message
        $finish;

    end
endmodule //counter_tb

`default_nettype wire

visualizer/com.vcd
$date
	Tue Oct 10 15:09:45 2023
$end
$version
	Icarus Verilog
$end
$timescale
	1ps
$end
$scope module com_tb $end
$var wire 10 ! y_out [9:0] $end
$var wire 11 " x_out [10:0] $end
$var wire 1 # valid_out $end
$var reg 1 $ clk_in $end
$var reg 1 % rst_in $end
$var reg 1 & tabulate_in $end
$var reg 1 ' valid_in $end
$var reg 11 ( x_in [10:0] $end
$var reg 10 ) y_in [9:0] $end
$scope module uut $end
$var wire 1 $ clk_in $end
$var wire 1 % rst_in $end
$var wire 1 & tabulate_in $end
$var wire 1 ' valid_in $end
$var wire 11 * x_in [10:0] $end
$var wire 10 + y_in [9:0] $end
$var wire 1 , valid_out_y $end
$var wire 1 - valid_out_x $end
$var wire 32 . remainder_y [31:0] $end
$var wire 32 / remainder_x [31:0] $end
$var wire 32 0 quotient_y [31:0] $end
$var wire 32 1 quotient_x [31:0] $end
$var wire 1 2 error_y $end
$var wire 1 3 error_x $end
$var wire 1 4 busy_y $end
$var wire 1 5 busy_x $end
$var parameter 64 6 total_pixels $end
$var reg 32 7 sum_of_x_pixels [31:0] $end
$var reg 32 8 sum_of_y_pixels [31:0] $end
$var reg 32 9 tally_of_pixels [31:0] $end
$var reg 1 : valid_division $end
$var reg 1 # valid_out $end
$var reg 11 ; x_out [10:0] $end
$var reg 10 < y_out [9:0] $end
$var integer 32 = state [31:0] $end
$scope module mydividerx $end
$var wire 1 $ clk_in $end
$var wire 1 : data_valid_in $end
$var wire 32 > dividend_in [31:0] $end
$var wire 32 ? divisor_in [31:0] $end
$var wire 1 % rst_in $end
$var parameter 32 @ DIVIDING $end
$var parameter 32 A RESTING $end
$var parameter 32 B WIDTH $end
$var reg 1 5 busy_out $end
$var reg 1 - data_valid_out $end
$var reg 32 C dividend [31:0] $end
$var reg 32 D divisor [31:0] $end
$var reg 1 3 error_out $end
$var reg 32 E quotient [31:0] $end
$var reg 32 F quotient_out [31:0] $end
$var reg 32 G remainder_out [31:0] $end
$var reg 1 H state $end
$upscope $end
$scope module mydividery $end
$var wire 1 $ clk_in $end
$var wire 1 : data_valid_in $end
$var wire 32 I dividend_in [31:0] $end
$var wire 32 J divisor_in [31:0] $end
$var wire 1 % rst_in $end
$var parameter 32 K DIVIDING $end
$var parameter 32 L RESTING $end
$var parameter 32 M WIDTH $end
$var reg 1 4 busy_out $end
$var reg 1 , data_valid_out $end
$var reg 32 N dividend [31:0] $end
$var reg 32 O divisor [31:0] $end
$var reg 1 2 error_out $end
$var reg 32 P quotient [31:0] $end
$var reg 32 Q quotient_out [31:0] $end
$var reg 32 R remainder_out [31:0] $end
$var reg 1 S state $end
$upscope $end
$upscope $end
$scope begin $ivl_for_loop0 $end
$var integer 32 T i [31:0] $end
$upscope $end
$scope begin $ivl_for_loop1 $end
$var integer 32 U i [31:0] $end
$upscope $end
$scope begin $ivl_for_loop2 $end
$var integer 32 V i [31:0] $end
$upscope $end
$scope begin $ivl_for_loop3 $end
$var integer 32 W i [31:0] $end
$upscope $end
$upscope $end
$enddefinitions $end
$comment Show the parameter values. $end
$dumpall
b100000 M
b0 L
b1 K
b100000 B
b0 A
b1 @
b11000000000000000000 6
$end
#0
$dumpvars
b0 W
b0 V
b0 U
b0 T
xS
bx R
bx Q
bx P
bx O
bx N
bx J
bx I
xH
bx G
bx F
bx E
bx D
bx C
bx ?
bx >
b0 =
bx <
bx ;
x:
bx 9
bx 8
bx 7
x5
x4
x3
x2
bx 1
bx 0
bx /
bx .
x-
x,
b0 +
b0 *
b0 )
b0 (
0'
0&
0%
0$
x#
bx "
bx !
$end
#5000
1$
#10000
0$
1%
#15000
0#
0:
b0 9
b0 ?
b0 J
b0 8
b0 I
b0 7
b0 >
b0 !
b0 <
b0 "
b0 ;
0,
0S
02
04
b0 .
b0 R
b0 O
b0 N
b0 P
0-
0H
03
05
b0 /
b0 G
b0 D
b0 C
b0 E
1$
#20000
0$
0%
#25000
1$
#30000
0$
1'
#35000
b1 9
b1 ?
b1 J
1$
#40000
0$
b1 (
b1 *
b1 T
#45000
b10 9
b10 ?
b10 J
b1 7
b1 >
1$
#50000
0$
b1 )
b1 +
b10 (
b10 *
b10 T
#55000
b11 9
b11 ?
b11 J
b1 8
b1 I
b11 7
b11 >
1$
#60000
0$
b11 (
b11 *
b11 T
#65000
b100 9
b100 ?
b100 J
b10 8
b10 I
b110 7
b110 >
1$
#70000
0$
b10 )
b10 +
b100 (
b100 *
b100 T
#75000
b101 9
b101 ?
b101 J
b100 8
b100 I
b1010 7
b1010 >
1$
#80000
0$
b101 (
b101 *
b101 T
#85000
b110 9
b110 ?
b110 J
b110 8
b110 I
b1111 7
b1111 >
1$
#90000
0$
b11 )
b11 +
b110 (
b110 *
b110 T
#95000
b111 9
b111 ?
b111 J
b1001 8
b1001 I
b10101 7
b10101 >
1$
#100000
0$
b111 (
b111 *
b111 T
#105000
b1000 9
b1000 ?
b1000 J
b1100 8
b1100 I
b11100 7
b11100 >
1$
#110000
0$
b100 )
b100 +
b1000 (
b1000 *
b1000 T
#115000
b1001 9
b1001 ?
b1001 J
b10000 8
b10000 I
b100100 7
b100100 >
1$
#120000
0$
b1001 (
b1001 *
b1001 T
#125000
b1010 9
b1010 ?
b1010 J
b10100 8
b10100 I
b101101 7
b101101 >
1$
#130000
0$
b101 )
b101 +
b1010 (
b1010 *
b1010 T
#135000
b1011 9
b1011 ?
b1011 J
b11001 8
b11001 I
b110111 7
b110111 >
1$
#140000
0$
b1011 (
b1011 *
b1011 T
#145000
b1100 9
b1100 ?
b1100 J
b11110 8
b11110 I
b1000010 7
b1000010 >
1$
#150000
0$
b110 )
b110 +
b1100 (
b1100 *
b1100 T
#155000
b1101 9
b1101 ?
b1101 J
b100100 8
b100100 I
b1001110 7
b1001110 >
1$
#160000
0$
b1101 (
b1101 *
b1101 T
#165000
b1110 9
b1110 ?
b1110 J
b101010 8
b101010 I
b1011011 7
b1011011 >
1$
#170000
0$
b111 )
b111 +
b1110 (
b1110 *
b1110 T
#175000
b1111 9
b1111 ?
b1111 J
b110001 8
b110001 I
b1101001 7
b1101001 >
1$
#180000
0$
b1111 (
b1111 *
b1111 T
#185000
b10000 9
b10000 ?
b10000 J
b111000 8
b111000 I
b1111000 7
b1111000 >
1$
#190000
0$
b1000 )
b1000 +
b10000 (
b10000 *
b10000 T
#195000
b10001 9
b10001 ?
b10001 J
b1000000 8
b1000000 I
b10001000 7
b10001000 >
1$
#200000
0$
b10001 (
b10001 *
b10001 T
#205000
b10010 9
b10010 ?
b10010 J
b1001000 8
b1001000 I
b10011001 7
b10011001 >
1$
#210000
0$
b1001 )
b1001 +
b10010 (
b10010 *
b10010 T
#215000
b10011 9
b10011 ?
b10011 J
b1010001 8
b1010001 I
b10101011 7
b10101011 >
1$
#220000
0$
b10011 (
b10011 *
b10011 T
#225000
b10100 9
b10100 ?
b10100 J
b1011010 8
b1011010 I
b10111110 7
b10111110 >
1$
#230000
0$
b1010 )
b1010 +
b10100 (
b10100 *
b10100 T
#235000
b10101 9
b10101 ?
b10101 J
b1100100 8
b1100100 I
b11010010 7
b11010010 >
1$
#240000
0$
b10101 (
b10101 *
b10101 T
#245000
b10110 9
b10110 ?
b10110 J
b1101110 8
b1101110 I
b11100111 7
b11100111 >
1$
#250000
0$
b1011 )
b1011 +
b10110 (
b10110 *
b10110 T
#255000
b10111 9
b10111 ?
b10111 J
b1111001 8
b1111001 I
b11111101 7
b11111101 >
1$
#260000
0$
b10111 (
b10111 *
b10111 T
#265000
b11000 9
b11000 ?
b11000 J
b10000100 8
b10000100 I
b100010100 7
b100010100 >
1$
#270000
0$
b1100 )
b1100 +
b11000 (
b11000 *
b11000 T
#275000
b11001 9
b11001 ?
b11001 J
b10010000 8
b10010000 I
b100101100 7
b100101100 >
1$
#280000
0$
b11001 (
b11001 *
b11001 T
#285000
b11010 9
b11010 ?
b11010 J
b10011100 8
b10011100 I
b101000101 7
b101000101 >
1$
#290000
0$
b1101 )
b1101 +
b11010 (
b11010 *
b11010 T
#295000
b11011 9
b11011 ?
b11011 J
b10101001 8
b10101001 I
b101011111 7
b101011111 >
1$
#300000
0$
b11011 (
b11011 *
b11011 T
#305000
b11100 9
b11100 ?
b11100 J
b10110110 8
b10110110 I
b101111010 7
b101111010 >
1$
#310000
0$
b1110 )
b1110 +
b11100 (
b11100 *
b11100 T
#315000
b11101 9
b11101 ?
b11101 J
b11000100 8
b11000100 I
b110010110 7
b110010110 >
1$
#320000
0$
b11101 (
b11101 *
b11101 T
#325000
b11110 9
b11110 ?
b11110 J
b11010010 8
b11010010 I
b110110011 7
b110110011 >
1$
#330000
0$
b1111 )
b1111 +
b11110 (
b11110 *
b11110 T
#335000
b11111 9
b11111 ?
b11111 J
b11100001 8
b11100001 I
b111010001 7
b111010001 >
1$
#340000
0$
b11111 (
b11111 *
b11111 T
#345000
b100000 9
b100000 ?
b100000 J
b11110000 8
b11110000 I
b111110000 7
b111110000 >
1$
#350000
0$
b10000 )
b10000 +
b100000 (
b100000 *
b100000 T
#355000
b100001 9
b100001 ?
b100001 J
b100000000 8
b100000000 I
b1000010000 7
b1000010000 >
1$
#360000
0$
b100001 (
b100001 *
b100001 T
#365000
b100010 9
b100010 ?
b100010 J
b100010000 8
b100010000 I
b1000110001 7
b1000110001 >
1$
#370000
0$
b10001 )
b10001 +
b100010 (
b100010 *
b100010 T
#375000
b100011 9
b100011 ?
b100011 J
b100100001 8
b100100001 I
b1001010011 7
b1001010011 >
1$
#380000
0$
b100011 (
b100011 *
b100011 T
#385000
b100100 9
b100100 ?
b100100 J
b100110010 8
b100110010 I
b1001110110 7
b1001110110 >
1$
#390000
0$
b10010 )
b10010 +
b100100 (
b100100 *
b100100 T
#395000
b100101 9
b100101 ?
b100101 J
b101000100 8
b101000100 I
b1010011010 7
b1010011010 >
1$
#400000
0$
b100101 (
b100101 *
b100101 T
#405000
b100110 9
b100110 ?
b100110 J
b101010110 8
b101010110 I
b1010111111 7
b1010111111 >
1$
#410000
0$
b10011 )
b10011 +
b100110 (
b100110 *
b100110 T
#415000
b100111 9
b100111 ?
b100111 J
b101101001 8
b101101001 I
b1011100101 7
b1011100101 >
1$
#420000
0$
b100111 (
b100111 *
b100111 T
#425000
b101000 9
b101000 ?
b101000 J
b101111100 8
b101111100 I
b1100001100 7
b1100001100 >
1$
#430000
0$
b10100 )
b10100 +
b101000 (
b101000 *
b101000 T
#435000
b101001 9
b101001 ?
b101001 J
b110010000 8
b110010000 I
b1100110100 7
b1100110100 >
1$
#440000
0$
b101001 (
b101001 *
b101001 T
#445000
b101010 9
b101010 ?
b101010 J
b110100100 8
b110100100 I
b1101011101 7
b1101011101 >
1$
#450000
0$
b10101 )
b10101 +
b101010 (
b101010 *
b101010 T
#455000
b101011 9
b101011 ?
b101011 J
b110111001 8
b110111001 I
b1110000111 7
b1110000111 >
1$
#460000
0$
b101011 (
b101011 *
b101011 T
#465000
b101100 9
b101100 ?
b101100 J
b111001110 8
b111001110 I
b1110110010 7
b1110110010 >
1$
#470000
0$
b10110 )
b10110 +
b101100 (
b101100 *
b101100 T
#475000
b101101 9
b101101 ?
b101101 J
b111100100 8
b111100100 I
b1111011110 7
b1111011110 >
1$
#480000
0$
b101101 (
b101101 *
b101101 T
#485000
b101110 9
b101110 ?
b101110 J
b111111010 8
b111111010 I
b10000001011 7
b10000001011 >
1$
#490000
0$
b10111 )
b10111 +
b101110 (
b101110 *
b101110 T
#495000
b101111 9
b101111 ?
b101111 J
b1000010001 8
b1000010001 I
b10000111001 7
b10000111001 >
1$
#500000
0$
b101111 (
b101111 *
b101111 T
#505000
b110000 9
b110000 ?
b110000 J
b1000101000 8
b1000101000 I
b10001101000 7
b10001101000 >
1$
#510000
0$
b11000 )
b11000 +
b110000 (
b110000 *
b110000 T
#515000
b110001 9
b110001 ?
b110001 J
b1001000000 8
b1001000000 I
b10010011000 7
b10010011000 >
1$
#520000
0$
b110001 (
b110001 *
b110001 T
#525000
b110010 9
b110010 ?
b110010 J
b1001011000 8
b1001011000 I
b10011001001 7
b10011001001 >
1$
#530000
0$
b11001 )
b11001 +
b110010 (
b110010 *
b110010 T
#535000
b110011 9
b110011 ?
b110011 J
b1001110001 8
b1001110001 I
b10011111011 7
b10011111011 >
1$
#540000
0$
b110011 (
b110011 *
b110011 T
#545000
b110100 9
b110100 ?
b110100 J
b1010001010 8
b1010001010 I
b10100101110 7
b10100101110 >
1$
#550000
0$
b11010 )
b11010 +
b110100 (
b110100 *
b110100 T
#555000
b110101 9
b110101 ?
b110101 J
b1010100100 8
b1010100100 I
b10101100010 7
b10101100010 >
1$
#560000
0$
b110101 (
b110101 *
b110101 T
#565000
b110110 9
b110110 ?
b110110 J
b1010111110 8
b1010111110 I
b10110010111 7
b10110010111 >
1$
#570000
0$
b11011 )
b11011 +
b110110 (
b110110 *
b110110 T
#575000
b110111 9
b110111 ?
b110111 J
b1011011001 8
b1011011001 I
b10111001101 7
b10111001101 >
1$
#580000
0$
b110111 (
b110111 *
b110111 T
#585000
b111000 9
b111000 ?
b111000 J
b1011110100 8
b1011110100 I
b11000000100 7
b11000000100 >
1$
#590000
0$
b11100 )
b11100 +
b111000 (
b111000 *
b111000 T
#595000
b111001 9
b111001 ?
b111001 J
b1100010000 8
b1100010000 I
b11000111100 7
b11000111100 >
1$
#600000
0$
b111001 (
b111001 *
b111001 T
#605000
b111010 9
b111010 ?
b111010 J
b1100101100 8
b1100101100 I
b11001110101 7
b11001110101 >
1$
#610000
0$
b11101 )
b11101 +
b111010 (
b111010 *
b111010 T
#615000
b111011 9
b111011 ?
b111011 J
b1101001001 8
b1101001001 I
b11010101111 7
b11010101111 >
1$
#620000
0$
b111011 (
b111011 *
b111011 T
#625000
b111100 9
b111100 ?
b111100 J
b1101100110 8
b1101100110 I
b11011101010 7
b11011101010 >
1$
#630000
0$
b11110 )
b11110 +
b111100 (
b111100 *
b111100 T
#635000
b111101 9
b111101 ?
b111101 J
b1110000100 8
b1110000100 I
b11100100110 7
b11100100110 >
1$
#640000
0$
b111101 (
b111101 *
b111101 T
#645000
b111110 9
b111110 ?
b111110 J
b1110100010 8
b1110100010 I
b11101100011 7
b11101100011 >
1$
#650000
0$
b11111 )
b11111 +
b111110 (
b111110 *
b111110 T
#655000
b111111 9
b111111 ?
b111111 J
b1111000001 8
b1111000001 I
b11110100001 7
b11110100001 >
1$
#660000
0$
b111111 (
b111111 *
b111111 T
#665000
b1000000 9
b1000000 ?
b1000000 J
b1111100000 8
b1111100000 I
b11111100000 7
b11111100000 >
1$
#670000
0$
b100000 )
b100000 +
b1000000 (
b1000000 *
b1000000 T
#675000
b1000001 9
b1000001 ?
b1000001 J
b10000000000 8
b10000000000 I
b100000100000 7
b100000100000 >
1$
#680000
0$
b1000001 (
b1000001 *
b1000001 T
#685000
b1000010 9
b1000010 ?
b1000010 J
b10000100000 8
b10000100000 I
b100001100001 7
b100001100001 >
1$
#690000
0$
b100001 )
b100001 +
b1000010 (
b1000010 *
b1000010 T
#695000
b1000011 9
b1000011 ?
b1000011 J
b10001000001 8
b10001000001 I
b100010100011 7
b100010100011 >
1$
#700000
0$
b1000011 (
b1000011 *
b1000011 T
#705000
b1000100 9
b1000100 ?
b1000100 J
b10001100010 8
b10001100010 I
b100011100110 7
b100011100110 >
1$
#710000
0$
b100010 )
b100010 +
b1000100 (
b1000100 *
b1000100 T
#715000
b1000101 9
b1000101 ?
b1000101 J
b10010000100 8
b10010000100 I
b100100101010 7
b100100101010 >
1$
#720000
0$
b1000101 (
b1000101 *
b1000101 T
#725000
b1000110 9
b1000110 ?
b1000110 J
b10010100110 8
b10010100110 I
b100101101111 7
b100101101111 >
1$
#730000
0$
b100011 )
b100011 +
b1000110 (
b1000110 *
b1000110 T
#735000
b1000111 9
b1000111 ?
b1000111 J
b10011001001 8
b10011001001 I
b100110110101 7
b100110110101 >
1$
#740000
0$
b1000111 (
b1000111 *
b1000111 T
#745000
b1001000 9
b1001000 ?
b1001000 J
b10011101100 8
b10011101100 I
b100111111100 7
b100111111100 >
1$
#750000
0$
b100100 )
b100100 +
b1001000 (
b1001000 *
b1001000 T
#755000
b1001001 9
b1001001 ?
b1001001 J
b10100010000 8
b10100010000 I
b101001000100 7
b101001000100 >
1$
#760000
0$
b1001001 (
b1001001 *
b1001001 T
#765000
b1001010 9
b1001010 ?
b1001010 J
b10100110100 8
b10100110100 I
b101010001101 7
b101010001101 >
1$
#770000
0$
b100101 )
b100101 +
b1001010 (
b1001010 *
b1001010 T
#775000
b1001011 9
b1001011 ?
b1001011 J
b10101011001 8
b10101011001 I
b101011010111 7
b101011010111 >
1$
#780000
0$
b1001011 (
b1001011 *
b1001011 T
#785000
b1001100 9
b1001100 ?
b1001100 J
b10101111110 8
b10101111110 I
b101100100010 7
b101100100010 >
1$
#790000
0$
b100110 )
b100110 +
b1001100 (
b1001100 *
b1001100 T
#795000
b1001101 9
b1001101 ?
b1001101 J
b10110100100 8
b10110100100 I
b101101101110 7
b101101101110 >
1$
#800000
0$
b1001101 (
b1001101 *
b1001101 T
#805000
b1001110 9
b1001110 ?
b1001110 J
b10111001010 8
b10111001010 I
b101110111011 7
b101110111011 >
1$
#810000
0$
b100111 )
b100111 +
b1001110 (
b1001110 *
b1001110 T
#815000
b1001111 9
b1001111 ?
b1001111 J
b10111110001 8
b10111110001 I
b110000001001 7
b110000001001 >
1$
#820000
0$
b1001111 (
b1001111 *
b1001111 T
#825000
b1010000 9
b1010000 ?
b1010000 J
b11000011000 8
b11000011000 I
b110001011000 7
b110001011000 >
1$
#830000
0$
b101000 )
b101000 +
b1010000 (
b1010000 *
b1010000 T
#835000
b1010001 9
b1010001 ?
b1010001 J
b11001000000 8
b11001000000 I
b110010101000 7
b110010101000 >
1$
#840000
0$
b1010001 (
b1010001 *
b1010001 T
#845000
b1010010 9
b1010010 ?
b1010010 J
b11001101000 8
b11001101000 I
b110011111001 7
b110011111001 >
1$
#850000
0$
b101001 )
b101001 +
b1010010 (
b1010010 *
b1010010 T
#855000
b1010011 9
b1010011 ?
b1010011 J
b11010010001 8
b11010010001 I
b110101001011 7
b110101001011 >
1$
#860000
0$
b1010011 (
b1010011 *
b1010011 T
#865000
b1010100 9
b1010100 ?
b1010100 J
b11010111010 8
b11010111010 I
b110110011110 7
b110110011110 >
1$
#870000
0$
b101010 )
b101010 +
b1010100 (
b1010100 *
b1010100 T
#875000
b1010101 9
b1010101 ?
b1010101 J
b11011100100 8
b11011100100 I
b110111110010 7
b110111110010 >
1$
#880000
0$
b1010101 (
b1010101 *
b1010101 T
#885000
b1010110 9
b1010110 ?
b1010110 J
b11100001110 8
b11100001110 I
b111001000111 7
b111001000111 >
1$
#890000
0$
b101011 )
b101011 +
b1010110 (
b1010110 *
b1010110 T
#895000
b1010111 9
b1010111 ?
b1010111 J
b11100111001 8
b11100111001 I
b111010011101 7
b111010011101 >
1$
#900000
0$
b1010111 (
b1010111 *
b1010111 T
#905000
b1011000 9
b1011000 ?
b1011000 J
b11101100100 8
b11101100100 I
b111011110100 7
b111011110100 >
1$
#910000
0$
b101100 )
b101100 +
b1011000 (
b1011000 *
b1011000 T
#915000
b1011001 9
b1011001 ?
b1011001 J
b11110010000 8
b11110010000 I
b111101001100 7
b111101001100 >
1$
#920000
0$
b1011001 (
b1011001 *
b1011001 T
#925000
b1011010 9
b1011010 ?
b1011010 J
b11110111100 8
b11110111100 I
b111110100101 7
b111110100101 >
1$
#930000
0$
b101101 )
b101101 +
b1011010 (
b1011010 *
b1011010 T
#935000
b1011011 9
b1011011 ?
b1011011 J
b11111101001 8
b11111101001 I
b111111111111 7
b111111111111 >
1$
#940000
0$
b1011011 (
b1011011 *
b1011011 T
#945000
b1011100 9
b1011100 ?
b1011100 J
b100000010110 8
b100000010110 I
b1000001011010 7
b1000001011010 >
1$
#950000
0$
b101110 )
b101110 +
b1011100 (
b1011100 *
b1011100 T
#955000
b1011101 9
b1011101 ?
b1011101 J
b100001000100 8
b100001000100 I
b1000010110110 7
b1000010110110 >
1$
#960000
0$
b1011101 (
b1011101 *
b1011101 T
#965000
b1011110 9
b1011110 ?
b1011110 J
b100001110010 8
b100001110010 I
b1000100010011 7
b1000100010011 >
1$
#970000
0$
b101111 )
b101111 +
b1011110 (
b1011110 *
b1011110 T
#975000
b1011111 9
b1011111 ?
b1011111 J
b100010100001 8
b100010100001 I
b1000101110001 7
b1000101110001 >
1$
#980000
0$
b1011111 (
b1011111 *
b1011111 T
#985000
b1100000 9
b1100000 ?
b1100000 J
b100011010000 8
b100011010000 I
b1000111010000 7
b1000111010000 >
1$
#990000
0$
b110000 )
b110000 +
b1100000 (
b1100000 *
b1100000 T
#995000
b1100001 9
b1100001 ?
b1100001 J
b100100000000 8
b100100000000 I
b1001000110000 7
b1001000110000 >
1$
#1000000
0$
b1100001 (
b1100001 *
b1100001 T
#1005000
b1100010 9
b1100010 ?
b1100010 J
b100100110000 8
b100100110000 I
b1001010010001 7
b1001010010001 >
1$
#1010000
0$
b110001 )
b110001 +
b1100010 (
b1100010 *
b1100010 T
#1015000
b1100011 9
b1100011 ?
b1100011 J
b100101100001 8
b100101100001 I
b1001011110011 7
b1001011110011 >
1$
#1020000
0$
b1100011 (
b1100011 *
b1100011 T
#1025000
b1100100 9
b1100100 ?
b1100100 J
b100110010010 8
b100110010010 I
b1001101010110 7
b1001101010110 >
1$
#1030000
0$
b110010 )
b110010 +
b1100100 (
b1100100 *
b1100100 T
#1035000
b1100101 9
b1100101 ?
b1100101 J
b100111000100 8
b100111000100 I
b1001110111010 7
b1001110111010 >
1$
#1040000
0$
b1100101 (
b1100101 *
b1100101 T
#1045000
b1100110 9
b1100110 ?
b1100110 J
b100111110110 8
b100111110110 I
b1010000011111 7
b1010000011111 >
1$
#1050000
0$
b110011 )
b110011 +
b1100110 (
b1100110 *
b1100110 T
